15-selfproc/machine/decl.v

reg [ 3:0]  t  = 0;
reg [31:0]  ip = 0;
reg [ 7:0]  ir;
reg         cp = 0;
reg [31:0]  ea;

15-v220209/machine/cpu.v
module cpu
(
    input   wire            clock,
    input   wire            locked,
    input   wire            resetn,
    
    // Память
    output  reg     [31:0]  address,
    input   wire    [ 7:0]  i_data,
    output  reg     [ 7:0]  o_data,
    output  reg             we,
    
    // Регистры
    output  reg     [7:0]   ra,
    output  reg     [7:0]   rb,
    input   wire    [31:0]  rav,
    input   wire    [31:0]  rbv,
    output  reg     [31:0]  rdata,
    output  reg             rw,
    
    // Стек
    output  reg     [ 9:0]  sp,
    input   wire    [31:0]  spi,
    output  reg     [31:0]  spo,
    output  reg             spw
);

`include "decl.v"

assign address = cp ? ea : ip;

always @(posedge clock) 
if (locked == 0 || resetn == 0) begin ip <= 0; t <= 0; end
else if (locked) begin

    we <= 0;
    rw <= 0;
    ip <= ip + 1;

    // Считывание опкода
    if (t == 0) begin
        
        t  <= 1;
        ir <= i_data;
    
    end

    // Исполнение операции
    casex (t ? ir : i_data)

        // 3T MOV ra, rb
        8'b00000000: case (t)

            1: begin t <= 2; rb <= i_data; end           
            2: begin t <= 0; ra <= i_data; rdata <= rbv; rw <= 1; end
        
        endcase        
        
        // 6T MOV ra, i32
        8'b00000001: case (t)
        
            1: begin t <= 2; ra <= i_data; end                            
            2: begin t <= 3; rdata <= i_data; end
            3: begin t <= 4; rdata[ 15:8] <= i_data; end
            4: begin t <= 5; rdata[23:16] <= i_data; end
            5: begin t <= 0; rdata[31:24] <= i_data; rw <= 1; end
        
        endcase
        
        // 3T MOV ra, i8|s8
        8'b0000001x: case (t)
        
            1: begin t <= 2; ra <= i_data; end            
            2: begin t <= 0; rdata <= ir[0] ? {{24{i_data[7]}}, i_data[7:0]} : i_data; rw <= 1; end

        endcase
        
        // 4T/7T MOV[B,D] ra, [rb]
        8'b0000010x: case (t)
            
            // Прочесть операнды
            1: begin t <= 2; rb <= i_data; end
            2: begin t <= 3; ra <= i_data; cp <= 1; ea <= rbv; end
            // Запись результата, если 8 бит
            3: begin 

                //                 32  8
                t       <= ir[0] ? 4 : 0; 
                rw      <= ir[0] ? 0 : 1;
                cp      <= ir[0];
                ip      <= ir[0] ? ip-3 : ip;
                ea      <= ea + 1;
                rdata   <= i_data; 
                
            end
            // Дочитать 24 бита и записать результат
            4: begin t <= 5; rdata[ 15:8] <= i_data; ea <= ea + 1; end
            5: begin t <= 6; rdata[23:16] <= i_data; ea <= ea + 1; end
            6: begin t <= 0; rdata[31:24] <= i_data; rw <= 1; cp <= 0; end

        endcase
        
        // 8T/5T MOV[B|D] [rb], ra
        8'b0000011x: case (t)
        
            1: begin t <= 2; rb <= i_data; end
            2: begin t <= 3; ra <= i_data; end
            3: begin

                t       <= 4;
                ea      <= rbv; 
                we      <= 1; 
                cp      <= 1; 
                o_data  <= rav[7:0];
                
            end
            // Запись 8 бит
            4: begin 
            
                t       <= ir[0] ? 5 : 0;
                ip      <= ir[0] ? ip-4 : ip-1;
                cp      <= ir[0];
                we      <= ir[0];
                ea      <= ea + 1;
                o_data  <= rav[15:8];
            
            end
            // Запись 32 бит
            5: begin t <= 6; we <= 1; ea <= ea + 1; o_data <= rav[23:16]; end
            6: begin t <= 7; we <= 1; ea <= ea + 1; o_data <= rav[31:24]; end
            7: begin t <= 0; cp <= 0; end
        
        endcase

    endcase

end

endmodule

15-v220209/machine/tb.v
`timescale 10ns / 1ns
module tb;
// -----------------------------------------------------------------------------
reg clock;
reg clock_25;
reg clock_50;

always #0.5 clock    = ~clock;
always #1.0 clock_50 = ~clock_50;
always #2.0 clock_25 = ~clock_25;

initial begin clock = 0; clock_25 = 0; clock_50 = 0; #2000 $finish; end
initial begin $dumpfile("tb.vcd"); $dumpvars(0, tb); end
// -----------------------------------------------------------------------------
initial begin $readmemh("tb.hex", memory, 0); end
// -----------------------------------------------------------------------------

// Память
reg [ 7:0] memory[1024*1024];
reg [31:0] address;
reg [ 7:0] i_data;
reg [ 7:0] o_data;

// Регистры
reg  [31:0] regs[256];
wire [ 7:0] ra;
wire [ 7:0] rb;
wire [31:0] rdata;
wire        rw;
wire [31:0] rav = ra ? regs[ra] : 0;
wire [31:0] rbv = rb ? regs[rb] : 0;

// Стек
reg  [31:0] stack[1024];        // 4kb стек
wire [ 9:0] sp;

always @(posedge clock) begin
    
    i_data <= memory[address[19:0]];
    if (we) memory[address[19:0]] <= o_data;
    
    // Запись в регистры
    if (rw) regs[ra] <= rdata;

end
// -----------------------------------------------------------------------------

cpu FoxlisicProcessor
(
    .clock      (clock_25),
    .locked     (1'b1),
    .resetn     (1'b1),
    
    // Память
    .address    (address),
    .i_data     (i_data),
    .o_data     (o_data),
    .we         (we),
    // Регистры
    .ra         (ra),
    .rb         (rb),
    .rav        (rav),
    .rbv        (rbv),
    .rdata      (rdata),
    .rw         (rw)
);

endmodule

15-v220209/machine/tb.vcd
$date
	Mon Feb 07 14:25:10 2022
$end
$version
	Icarus Verilog
$end
$timescale
	1ns
$end
$scope module tb $end
$var wire 1 ! we $end
$var wire 1 " rw $end
$var wire 32 # rdata [31:0] $end
$var wire 32 $ rbv [31:0] $end
$var wire 8 % rb [7:0] $end
$var wire 32 & rav [31:0] $end
$var wire 8 ' ra [7:0] $end
$var wire 8 ( o_data [7:0] $end
$var wire 32 ) address [31:0] $end
$var reg 1 * clock $end
$var reg 1 + clock_25 $end
$var reg 1 , clock_50 $end
$var reg 8 - i_data [7:0] $end
$scope module FoxlisicProcessor $end
$var wire 1 + clock $end
$var wire 8 . i_data [7:0] $end
$var wire 1 / locked $end
$var wire 32 0 rav [31:0] $end
$var wire 32 1 rbv [31:0] $end
$var wire 1 2 resetn $end
$var wire 32 3 address [31:0] $end
$var reg 1 4 cp $end
$var reg 32 5 ea [31:0] $end
$var reg 32 6 ip [31:0] $end
$var reg 8 7 ir [7:0] $end
$var reg 8 8 o_data [7:0] $end
$var reg 8 9 ra [7:0] $end
$var reg 8 : rb [7:0] $end
$var reg 32 ; rdata [31:0] $end
$var reg 1 " rw $end
$var reg 4 < t [3:0] $end
$var reg 1 ! we $end
$upscope $end
$upscope $end
$enddefinitions $end
#0
$dumpvars
b0 <
bx ;
bx :
bx 9
bx 8
bx 7
b0 6
bx 5
04
b0 3
12
bx 1
bx 0
1/
bx .
bx -
0,
0+
0*
b0 )
bx (
bx '
bx &
bx %
bx $
bx #
x"
x!
$end
#5
b1 -
b1 .
1*
#10
0*
1,
#15
1*
#20
b1 )
b1 3
b1 7
b1 <
b1 6
0"
0!
0*
0,
1+
#25
b1111 -
b1111 .
1*
#30
0*
1,
#35
1*
#40
0*
0,
0+
#45
1*
#50
0*
1,
#55
1*
#60
b10 )
b10 3
b1111 '
b1111 9
b10 <
b10 6
0*
0,
1+
#65
b10010 -
b10010 .
1*
#70
0*
1,
#75
1*
#80
0*
0,
0+
#85
1*
#90
0*
1,
#95
1*
#100
b11 )
b11 3
b10010 #
b10010 ;
b11 <
b11 6
0*
0,
1+
#105
b110100 -
b110100 .
1*
#110
0*
1,
#115
1*
#120
0*
0,
0+
#125
1*
#130
0*
1,
#135
1*
#140
b100 )
b100 3
b11010000010010 #
b11010000010010 ;
b100 <
b100 6
0*
0,
1+
#145
b1010110 -
b1010110 .
1*
#150
0*
1,
#155
1*
#160
0*
0,
0+
#165
1*
#170
0*
1,
#175
1*
#180
b101 )
b101 3
b10101100011010000010010 #
b10101100011010000010010 ;
b101 <
b101 6
0*
0,
1+
#185
b1110111 -
b1110111 .
1*
#190
0*
1,
#195
1*
#200
0*
0,
0+
#205
1*
#210
0*
1,
#215
1*
#220
b110 )
b110 3
1"
b1110111010101100011010000010010 #
b1110111010101100011010000010010 ;
b0 <
b110 6
0*
0,
1+
#225
b1110111010101100011010000010010 &
b1110111010101100011010000010010 0
b111 -
b111 .
1*
#230
0*
1,
#235
1*
#240
0*
0,
0+
#245
1*
#250
0*
1,
#255
1*
#260
b111 )
b111 3
b111 7
b1 <
b111 6
0"
0*
0,
1+
#265
b0 -
b0 .
1*
#270
0*
1,
#275
1*
#280
0*
0,
0+
#285
1*
#290
0*
1,
#295
1*
#300
b0 $
b0 1
b1000 )
b1000 3
b0 %
b0 :
b10 <
b1000 6
0*
0,
1+
#305
b1111 -
b1111 .
1*
#310
0*
1,
#315
1*
#320
0*
0,
0+
#325
1*
#330
0*
1,
#335
1*
#340
b1001 )
b1001 3
b11 <
b1001 6
0*
0,
1+
#345
b1 -
b1 .
1*
#350
0*
1,
#355
1*
#360
0*
0,
0+
#365
1*
#370
0*
1,
#375
1*
#380
b0 )
b0 3
b10010 (
b10010 8
14
1!
b0 5
b100 <
b1010 6
0*
0,
1+
#385
1*
#390
0*
1,
#395
b10010 -
b10010 .
1*
#400
0*
0,
0+
#405
1*
#410
0*
1,
#415
1*
#420
b1 )
b1 3
b110100 (
b110100 8
b1 5
b101 <
b110 6
1!
0*
0,
1+
#425
b1111 -
b1111 .
1*
#430
0*
1,
#435
b110100 -
b110100 .
1*
#440
0*
0,
0+
#445
1*
#450
0*
1,
#455
1*
#460
b10 )
b10 3
b1010110 (
b1010110 8
b10 5
b110 <
b111 6
1!
0*
0,
1+
#465
b10010 -
b10010 .
1*
#470
0*
1,
#475
b1010110 -
b1010110 .
1*
#480
0*
0,
0+
#485
1*
#490
0*
1,
#495
1*
#500
b11 )
b11 3
b1110111 (
b1110111 8
b11 5
b111 <
b1000 6
1!
0*
0,
1+
#505
b110100 -
b110100 .
1*
#510
0*
1,
#515
b1110111 -
b1110111 .
1*
#520
0*
0,
0+
#525
1*
#530
0*
1,
#535
1*
#540
b1001 )
b1001 3
04
b0 <
b1001 6
0!
0*
0,
1+
#545
b1 -
b1 .
1*
#550
0*
1,
#555
1*
#560
0*
0,
0+
#565
1*
#570
0*
1,
#575
1*
#580
b1010 )
b1010 3
b1 7
b1 <
b1010 6
0*
0,
1+
#585
b1110 -
b1110 .
1*
#590
0*
1,
#595
1*
#600
0*
0,
0+
#605
1*
#610
0*
1,
#615
1*
#620
bx &
bx 0
b1011 )
b1011 3
b1110 '
b1110 9
b10 <
b1011 6
0*
0,
1+
#625
b10001 -
b10001 .
1*
#630
0*
1,
#635
1*
#640
0*
0,
0+
#645
1*
#650
0*
1,
#655
1*
#660
b1100 )
b1100 3
b10001 #
b10001 ;
b11 <
b1100 6
0*
0,
1+
#665
b100010 -
b100010 .
1*
#670
0*
1,
#675
1*
#680
0*
0,
0+
#685
1*
#690
0*
1,
#695
1*
#700
b1101 )
b1101 3
b10001000010001 #
b10001000010001 ;
b100 <
b1101 6
0*
0,
1+
#705
b110011 -
b110011 .
1*
#710
0*
1,
#715
1*
#720
0*
0,
0+
#725
1*
#730
0*
1,
#735
1*
#740
b1110 )
b1110 3
b1100110010001000010001 #
b1100110010001000010001 ;
b101 <
b1110 6
0*
0,
1+
#745
b1000100 -
b1000100 .
1*
#750
0*
1,
#755
1*
#760
0*
0,
0+
#765
1*
#770
0*
1,
#775
1*
#780
b1111 )
b1111 3
1"
b1000100001100110010001000010001 #
b1000100001100110010001000010001 ;
b0 <
b1111 6
0*
0,
1+
#785
b1000100001100110010001000010001 &
b1000100001100110010001000010001 0
bx -
bx .
1*
#790
0*
1,
#795
1*
#800
0*
0,
0+
#805
1*
#810
0*
1,
#815
1*
#820
b10000 )
b10000 3
bx 7
b1 <
b10000 6
0"
0*
0,
1+
#825
1*
#830
0*
1,
#835
1*
#840
0*
0,
0+
#845
1*
#850
0*
1,
#855
1*
#860
bx $
bx 1
b10001 )
b10001 3
bx %
bx :
b10 <
b10001 6
0*
0,
1+
#865
1*
#870
0*
1,
#875
1*
#880
0*
0,
0+
#885
1*
#890
0*
1,
#895
1*
#900
bx &
bx 0
b10010 )
b10010 3
1"
bx #
bx ;
bx '
bx 9
b0 <
b10010 6
0*
0,
1+
#905
1*
#910
0*
1,
#915
1*
#920
0*
0,
0+
#925
1*
#930
0*
1,
#935
1*
#940
b10011 )
b10011 3
b1 <
b10011 6
0"
0*
0,
1+
#945
1*
#950
0*
1,
#955
1*
#960
0*
0,
0+
#965
1*
#970
0*
1,
#975
1*
#980
b10100 )
b10100 3
b10 <
b10100 6
0*
0,
1+
#985
1*
#990
0*
1,
#995
1*
#1000
0*
0,
0+
#1005
1*
#1010
0*
1,
#1015
1*
#1020
b10101 )
b10101 3
1"
b0 <
b10101 6
0*
0,
1+
#1025
1*
#1030
0*
1,
#1035
1*
#1040
0*
0,
0+
#1045
1*
#1050
0*
1,
#1055
1*
#1060
b10110 )
b10110 3
b1 <
b10110 6
0"
0*
0,
1+
#1065
1*
#1070
0*
1,
#1075
1*
#1080
0*
0,
0+
#1085
1*
#1090
0*
1,
#1095
1*
#1100
b10111 )
b10111 3
b10 <
b10111 6
0*
0,
1+
#1105
1*
#1110
0*
1,
#1115
1*
#1120
0*
0,
0+
#1125
1*
#1130
0*
1,
#1135
1*
#1140
b11000 )
b11000 3
1"
b0 <
b11000 6
0*
0,
1+
#1145
1*
#1150
0*
1,
#1155
1*
#1160
0*
0,
0+
#1165
1*
#1170
0*
1,
#1175
1*
#1180
b11001 )
b11001 3
b1 <
b11001 6
0"
0*
0,
1+
#1185
1*
#1190
0*
1,
#1195
1*
#1200
0*
0,
0+
#1205
1*
#1210
0*
1,
#1215
1*
#1220
b11010 )
b11010 3
b10 <
b11010 6
0*
0,
1+
#1225
1*
#1230
0*
1,
#1235
1*
#1240
0*
0,
0+
#1245
1*
#1250
0*
1,
#1255
1*
#1260
b11011 )
b11011 3
1"
b0 <
b11011 6
0*
0,
1+
#1265
1*
#1270
0*
1,
#1275
1*
#1280
0*
0,
0+
#1285
1*
#1290
0*
1,
#1295
1*
#1300
b11100 )
b11100 3
b1 <
b11100 6
0"
0*
0,
1+
#1305
1*
#1310
0*
1,
#1315
1*
#1320
0*
0,
0+
#1325
1*
#1330
0*
1,
#1335
1*
#1340
b11101 )
b11101 3
b10 <
b11101 6
0*
0,
1+
#1345
1*
#1350
0*
1,
#1355
1*
#1360
0*
0,
0+
#1365
1*
#1370
0*
1,
#1375
1*
#1380
b11110 )
b11110 3
1"
b0 <
b11110 6
0*
0,
1+
#1385
1*
#1390
0*
1,
#1395
1*
#1400
0*
0,
0+
#1405
1*
#1410
0*
1,
#1415
1*
#1420
b11111 )
b11111 3
b1 <
b11111 6
0"
0*
0,
1+
#1425
1*
#1430
0*
1,
#1435
1*
#1440
0*
0,
0+
#1445
1*
#1450
0*
1,
#1455
1*
#1460
b100000 )
b100000 3
b10 <
b100000 6
0*
0,
1+
#1465
1*
#1470
0*
1,
#1475
1*
#1480
0*
0,
0+
#1485
1*
#1490
0*
1,
#1495
1*
#1500
b100001 )
b100001 3
1"
b0 <
b100001 6
0*
0,
1+
#1505
1*
#1510
0*
1,
#1515
1*
#1520
0*
0,
0+
#1525
1*
#1530
0*
1,
#1535
1*
#1540
b100010 )
b100010 3
b1 <
b100010 6
0"
0*
0,
1+
#1545
1*
#1550
0*
1,
#1555
1*
#1560
0*
0,
0+
#1565
1*
#1570
0*
1,
#1575
1*
#1580
b100011 )
b100011 3
b10 <
b100011 6
0*
0,
1+
#1585
1*
#1590
0*
1,
#1595
1*
#1600
0*
0,
0+
#1605
1*
#1610
0*
1,
#1615
1*
#1620
b100100 )
b100100 3
1"
b0 <
b100100 6
0*
0,
1+
#1625
1*
#1630
0*
1,
#1635
1*
#1640
0*
0,
0+
#1645
1*
#1650
0*
1,
#1655
1*
#1660
b100101 )
b100101 3
b1 <
b100101 6
0"
0*
0,
1+
#1665
1*
#1670
0*
1,
#1675
1*
#1680
0*
0,
0+
#1685
1*
#1690
0*
1,
#1695
1*
#1700
b100110 )
b100110 3
b10 <
b100110 6
0*
0,
1+
#1705
1*
#1710
0*
1,
#1715
1*
#1720
0*
0,
0+
#1725
1*
#1730
0*
1,
#1735
1*
#1740
b100111 )
b100111 3
1"
b0 <
b100111 6
0*
0,
1+
#1745
1*
#1750
0*
1,
#1755
1*
#1760
0*
0,
0+
#1765
1*
#1770
0*
1,
#1775
1*
#1780
b101000 )
b101000 3
b1 <
b101000 6
0"
0*
0,
1+
#1785
1*
#1790
0*
1,
#1795
1*
#1800
0*
0,
0+
#1805
1*
#1810
0*
1,
#1815
1*
#1820
b101001 )
b101001 3
b10 <
b101001 6
0*
0,
1+
#1825
1*
#1830
0*
1,
#1835
1*
#1840
0*
0,
0+
#1845
1*
#1850
0*
1,
#1855
1*
#1860
b101010 )
b101010 3
1"
b0 <
b101010 6
0*
0,
1+
#1865
1*
#1870
0*
1,
#1875
1*
#1880
0*
0,
0+
#1885
1*
#1890
0*
1,
#1895
1*
#1900
b101011 )
b101011 3
b1 <
b101011 6
0"
0*
0,
1+
#1905
1*
#1910
0*
1,
#1915
1*
#1920
0*
0,
0+
#1925
1*
#1930
0*
1,
#1935
1*
#1940
b101100 )
b101100 3
b10 <
b101100 6
0*
0,
1+
#1945
1*
#1950
0*
1,
#1955
1*
#1960
0*
0,
0+
#1965
1*
#1970
0*
1,
#1975
1*
#1980
b101101 )
b101101 3
1"
b0 <
b101101 6
0*
0,
1+
#1985
1*
#1990
0*
1,
#1995
1*
#2000
0*
0,
0+
#2005
1*
#2010
0*
1,
#2015
1*
#2020
b101110 )
b101110 3
b1 <
b101110 6
0"
0*
0,
1+
#2025
1*
#2030
0*
1,
#2035
1*
#2040
0*
0,
0+
#2045
1*
#2050
0*
1,
#2055
1*
#2060
b101111 )
b101111 3
b10 <
b101111 6
0*
0,
1+
#2065
1*
#2070
0*
1,
#2075
1*
#2080
0*
0,
0+
#2085
1*
#2090
0*
1,
#2095
1*
#2100
b110000 )
b110000 3
1"
b0 <
b110000 6
0*
0,
1+
#2105
1*
#2110
0*
1,
#2115
1*
#2120
0*
0,
0+
#2125
1*
#2130
0*
1,
#2135
1*
#2140
b110001 )
b110001 3
b1 <
b110001 6
0"
0*
0,
1+
#2145
1*
#2150
0*
1,
#2155
1*
#2160
0*
0,
0+
#2165
1*
#2170
0*
1,
#2175
1*
#2180
b110010 )
b110010 3
b10 <
b110010 6
0*
0,
1+
#2185
1*
#2190
0*
1,
#2195
1*
#2200
0*
0,
0+
#2205
1*
#2210
0*
1,
#2215
1*
#2220
b110011 )
b110011 3
1"
b0 <
b110011 6
0*
0,
1+
#2225
1*
#2230
0*
1,
#2235
1*
#2240
0*
0,
0+
#2245
1*
#2250
0*
1,
#2255
1*
#2260
b110100 )
b110100 3
b1 <
b110100 6
0"
0*
0,
1+
#2265
1*
#2270
0*
1,
#2275
1*
#2280
0*
0,
0+
#2285
1*
#2290
0*
1,
#2295
1*
#2300
b110101 )
b110101 3
b10 <
b110101 6
0*
0,
1+
#2305
1*
#2310
0*
1,
#2315
1*
#2320
0*
0,
0+
#2325
1*
#2330
0*
1,
#2335
1*
#2340
b110110 )
b110110 3
1"
b0 <
b110110 6
0*
0,
1+
#2345
1*
#2350
0*
1,
#2355
1*
#2360
0*
0,
0+
#2365
1*
#2370
0*
1,
#2375
1*
#2380
b110111 )
b110111 3
b1 <
b110111 6
0"
0*
0,
1+
#2385
1*
#2390
0*
1,
#2395
1*
#2400
0*
0,
0+
#2405
1*
#2410
0*
1,
#2415
1*
#2420
b111000 )
b111000 3
b10 <
b111000 6
0*
0,
1+
#2425
1*
#2430
0*
1,
#2435
1*
#2440
0*
0,
0+
#2445
1*
#2450
0*
1,
#2455
1*
#2460
b111001 )
b111001 3
1"
b0 <
b111001 6
0*
0,
1+
#2465
1*
#2470
0*
1,
#2475
1*
#2480
0*
0,
0+
#2485
1*
#2490
0*
1,
#2495
1*
#2500
b111010 )
b111010 3
b1 <
b111010 6
0"
0*
0,
1+
#2505
1*
#2510
0*
1,
#2515
1*
#2520
0*
0,
0+
#2525
1*
#2530
0*
1,
#2535
1*
#2540
b111011 )
b111011 3
b10 <
b111011 6
0*
0,
1+
#2545
1*
#2550
0*
1,
#2555
1*
#2560
0*
0,
0+
#2565
1*
#2570
0*
1,
#2575
1*
#2580
b111100 )
b111100 3
1"
b0 <
b111100 6
0*
0,
1+
#2585
1*
#2590
0*
1,
#2595
1*
#2600
0*
0,
0+
#2605
1*
#2610
0*
1,
#2615
1*
#2620
b111101 )
b111101 3
b1 <
b111101 6
0"
0*
0,
1+
#2625
1*
#2630
0*
1,
#2635
1*
#2640
0*
0,
0+
#2645
1*
#2650
0*
1,
#2655
1*
#2660
b111110 )
b111110 3
b10 <
b111110 6
0*
0,
1+
#2665
1*
#2670
0*
1,
#2675
1*
#2680
0*
0,
0+
#2685
1*
#2690
0*
1,
#2695
1*
#2700
b111111 )
b111111 3
1"
b0 <
b111111 6
0*
0,
1+
#2705
1*
#2710
0*
1,
#2715
1*
#2720
0*
0,
0+
#2725
1*
#2730
0*
1,
#2735
1*
#2740
b1000000 )
b1000000 3
b1 <
b1000000 6
0"
0*
0,
1+
#2745
1*
#2750
0*
1,
#2755
1*
#2760
0*
0,
0+
#2765
1*
#2770
0*
1,
#2775
1*
#2780
b1000001 )
b1000001 3
b10 <
b1000001 6
0*
0,
1+
#2785
1*
#2790
0*
1,
#2795
1*
#2800
0*
0,
0+
#2805
1*
#2810
0*
1,
#2815
1*
#2820
b1000010 )
b1000010 3
1"
b0 <
b1000010 6
0*
0,
1+
#2825
1*
#2830
0*
1,
#2835
1*
#2840
0*
0,
0+
#2845
1*
#2850
0*
1,
#2855
1*
#2860
b1000011 )
b1000011 3
b1 <
b1000011 6
0"
0*
0,
1+
#2865
1*
#2870
0*
1,
#2875
1*
#2880
0*
0,
0+
#2885
1*
#2890
0*
1,
#2895
1*
#2900
b1000100 )
b1000100 3
b10 <
b1000100 6
0*
0,
1+
#2905
1*
#2910
0*
1,
#2915
1*
#2920
0*
0,
0+
#2925
1*
#2930
0*
1,
#2935
1*
#2940
b1000101 )
b1000101 3
1"
b0 <
b1000101 6
0*
0,
1+
#2945
1*
#2950
0*
1,
#2955
1*
#2960
0*
0,
0+
#2965
1*
#2970
0*
1,
#2975
1*
#2980
b1000110 )
b1000110 3
b1 <
b1000110 6
0"
0*
0,
1+
#2985
1*
#2990
0*
1,
#2995
1*
#3000
0*
0,
0+
#3005
1*
#3010
0*
1,
#3015
1*
#3020
b1000111 )
b1000111 3
b10 <
b1000111 6
0*
0,
1+
#3025
1*
#3030
0*
1,
#3035
1*
#3040
0*
0,
0+
#3045
1*
#3050
0*
1,
#3055
1*
#3060
b1001000 )
b1001000 3
1"
b0 <
b1001000 6
0*
0,
1+
#3065
1*
#3070
0*
1,
#3075
1*
#3080
0*
0,
0+
#3085
1*
#3090
0*
1,
#3095
1*
#3100
b1001001 )
b1001001 3
b1 <
b1001001 6
0"
0*
0,
1+
#3105
1*
#3110
0*
1,
#3115
1*
#3120
0*
0,
0+
#3125
1*
#3130
0*
1,
#3135
1*
#3140
b1001010 )
b1001010 3
b10 <
b1001010 6
0*
0,
1+
#3145
1*
#3150
0*
1,
#3155
1*
#3160
0*
0,
0+
#3165
1*
#3170
0*
1,
#3175
1*
#3180
b1001011 )
b1001011 3
1"
b0 <
b1001011 6
0*
0,
1+
#3185
1*
#3190
0*
1,
#3195
1*
#3200
0*
0,
0+
#3205
1*
#3210
0*
1,
#3215
1*
#3220
b1001100 )
b1001100 3
b1 <
b1001100 6
0"
0*
0,
1+
#3225
1*
#3230
0*
1,
#3235
1*
#3240
0*
0,
0+
#3245
1*
#3250
0*
1,
#3255
1*
#3260
b1001101 )
b1001101 3
b10 <
b1001101 6
0*
0,
1+
#3265
1*
#3270
0*
1,
#3275
1*
#3280
0*
0,
0+
#3285
1*
#3290
0*
1,
#3295
1*
#3300
b1001110 )
b1001110 3
1"
b0 <
b1001110 6
0*
0,
1+
#3305
1*
#3310
0*
1,
#3315
1*
#3320
0*
0,
0+
#3325
1*
#3330
0*
1,
#3335
1*
#3340
b1001111 )
b1001111 3
b1 <
b1001111 6
0"
0*
0,
1+
#3345
1*
#3350
0*
1,
#3355
1*
#3360
0*
0,
0+
#3365
1*
#3370
0*
1,
#3375
1*
#3380
b1010000 )
b1010000 3
b10 <
b1010000 6
0*
0,
1+
#3385
1*
#3390
0*
1,
#3395
1*
#3400
0*
0,
0+
#3405
1*
#3410
0*
1,
#3415
1*
#3420
b1010001 )
b1010001 3
1"
b0 <
b1010001 6
0*
0,
1+
#3425
1*
#3430
0*
1,
#3435
1*
#3440
0*
0,
0+
#3445
1*
#3450
0*
1,
#3455
1*
#3460
b1010010 )
b1010010 3
b1 <
b1010010 6
0"
0*
0,
1+
#3465
1*
#3470
0*
1,
#3475
1*
#3480
0*
0,
0+
#3485
1*
#3490
0*
1,
#3495
1*
#3500
b1010011 )
b1010011 3
b10 <
b1010011 6
0*
0,
1+
#3505
1*
#3510
0*
1,
#3515
1*
#3520
0*
0,
0+
#3525
1*
#3530
0*
1,
#3535
1*
#3540
b1010100 )
b1010100 3
1"
b0 <
b1010100 6
0*
0,
1+
#3545
1*
#3550
0*
1,
#3555
1*
#3560
0*
0,
0+
#3565
1*
#3570
0*
1,
#3575
1*
#3580
b1010101 )
b1010101 3
b1 <
b1010101 6
0"
0*
0,
1+
#3585
1*
#3590
0*
1,
#3595
1*
#3600
0*
0,
0+
#3605
1*
#3610
0*
1,
#3615
1*
#3620
b1010110 )
b1010110 3
b10 <
b1010110 6
0*
0,
1+
#3625
1*
#3630
0*
1,
#3635
1*
#3640
0*
0,
0+
#3645
1*
#3650
0*
1,
#3655
1*
#3660
b1010111 )
b1010111 3
1"
b0 <
b1010111 6
0*
0,
1+
#3665
1*
#3670
0*
1,
#3675
1*
#3680
0*
0,
0+
#3685
1*
#3690
0*
1,
#3695
1*
#3700
b1011000 )
b1011000 3
b1 <
b1011000 6
0"
0*
0,
1+
#3705
1*
#3710
0*
1,
#3715
1*
#3720
0*
0,
0+
#3725
1*
#3730
0*
1,
#3735
1*
#3740
b1011001 )
b1011001 3
b10 <
b1011001 6
0*
0,
1+
#3745
1*
#3750
0*
1,
#3755
1*
#3760
0*
0,
0+
#3765
1*
#3770
0*
1,
#3775
1*
#3780
b1011010 )
b1011010 3
1"
b0 <
b1011010 6
0*
0,
1+
#3785
1*
#3790
0*
1,
#3795
1*
#3800
0*
0,
0+
#3805
1*
#3810
0*
1,
#3815
1*
#3820
b1011011 )
b1011011 3
b1 <
b1011011 6
0"
0*
0,
1+
#3825
1*
#3830
0*
1,
#3835
1*
#3840
0*
0,
0+
#3845
1*
#3850
0*
1,
#3855
1*
#3860
b1011100 )
b1011100 3
b10 <
b1011100 6
0*
0,
1+
#3865
1*
#3870
0*
1,
#3875
1*
#3880
0*
0,
0+
#3885
1*
#3890
0*
1,
#3895
1*
#3900
b1011101 )
b1011101 3
1"
b0 <
b1011101 6
0*
0,
1+
#3905
1*
#3910
0*
1,
#3915
1*
#3920
0*
0,
0+
#3925
1*
#3930
0*
1,
#3935
1*
#3940
b1011110 )
b1011110 3
b1 <
b1011110 6
0"
0*
0,
1+
#3945
1*
#3950
0*
1,
#3955
1*
#3960
0*
0,
0+
#3965
1*
#3970
0*
1,
#3975
1*
#3980
b1011111 )
b1011111 3
b10 <
b1011111 6
0*
0,
1+
#3985
1*
#3990
0*
1,
#3995
1*
#4000
0*
0,
0+
#4005
1*
#4010
0*
1,
#4015
1*
#4020
b1100000 )
b1100000 3
1"
b0 <
b1100000 6
0*
0,
1+
#4025
1*
#4030
0*
1,
#4035
1*
#4040
0*
0,
0+
#4045
1*
#4050
0*
1,
#4055
1*
#4060
b1100001 )
b1100001 3
b1 <
b1100001 6
0"
0*
0,
1+
#4065
1*
#4070
0*
1,
#4075
1*
#4080
0*
0,
0+
#4085
1*
#4090
0*
1,
#4095
1*
#4100
b1100010 )
b1100010 3
b10 <
b1100010 6
0*
0,
1+
#4105
1*
#4110
0*
1,
#4115
1*
#4120
0*
0,
0+
#4125
1*
#4130
0*
1,
#4135
1*
#4140
b1100011 )
b1100011 3
1"
b0 <
b1100011 6
0*
0,
1+
#4145
1*
#4150
0*
1,
#4155
1*
#4160
0*
0,
0+
#4165
1*
#4170
0*
1,
#4175
1*
#4180
b1100100 )
b1100100 3
b1 <
b1100100 6
0"
0*
0,
1+
#4185
1*
#4190
0*
1,
#4195
1*
#4200
0*
0,
0+
#4205
1*
#4210
0*
1,
#4215
1*
#4220
b1100101 )
b1100101 3
b10 <
b1100101 6
0*
0,
1+
#4225
1*
#4230
0*
1,
#4235
1*
#4240
0*
0,
0+
#4245
1*
#4250
0*
1,
#4255
1*
#4260
b1100110 )
b1100110 3
1"
b0 <
b1100110 6
0*
0,
1+
#4265
1*
#4270
0*
1,
#4275
1*
#4280
0*
0,
0+
#4285
1*
#4290
0*
1,
#4295
1*
#4300
b1100111 )
b1100111 3
b1 <
b1100111 6
0"
0*
0,
1+
#4305
1*
#4310
0*
1,
#4315
1*
#4320
0*
0,
0+
#4325
1*
#4330
0*
1,
#4335
1*
#4340
b1101000 )
b1101000 3
b10 <
b1101000 6
0*
0,
1+
#4345
1*
#4350
0*
1,
#4355
1*
#4360
0*
0,
0+
#4365
1*
#4370
0*
1,
#4375
1*
#4380
b1101001 )
b1101001 3
1"
b0 <
b1101001 6
0*
0,
1+
#4385
1*
#4390
0*
1,
#4395
1*
#4400
0*
0,
0+
#4405
1*
#4410
0*
1,
#4415
1*
#4420
b1101010 )
b1101010 3
b1 <
b1101010 6
0"
0*
0,
1+
#4425
1*
#4430
0*
1,
#4435
1*
#4440
0*
0,
0+
#4445
1*
#4450
0*
1,
#4455
1*
#4460
b1101011 )
b1101011 3
b10 <
b1101011 6
0*
0,
1+
#4465
1*
#4470
0*
1,
#4475
1*
#4480
0*
0,
0+
#4485
1*
#4490
0*
1,
#4495
1*
